tweet_requester/__init__.py
tweet_requester/analysis.py
tweet_requester/cache.py
tweet_requester/display.py
tweet_requester/session.py
tweet_requester-0.0.1.7.dist-info/LICENSE.txt
tweet_requester-0.0.1.7.dist-info/METADATA
tweet_requester-0.0.1.7.dist-info/WHEEL
tweet_requester-0.0.1.7.dist-info/top_level.txt
tweet_requester-0.0.1.7.dist-info/RECORD
