Metadata-Version: 2.1
Name: tweet-requester
Version: 0.0.1.7
Summary: Twitter API 1.1 Interaction Library with Cache and IPython interfaces
Home-page: https://github.com/RickyRenunciaProject/tweet_requester
Author: Torrien(https://github.com/Torrien)
Author-email: ebf.beltran@gmail.com
License: MIT
Project-URL: Bug Tracker, https://github.com/RickyRenunciaProject/tweet_requester/issues
Project-URL: Project Page, https://libarchivist.com/rrp/rickyrenuncia/index
Platform: UNKNOWN
Classifier: License :: OSI Approved :: MIT License
Classifier: Programming Language :: Python :: 3
Classifier: Operating System :: OS Independent
Requires-Python: >=3.7
License-File: LICENSE.txt
Requires-Dist: ipython (>=7.25.0)
Requires-Dist: google-cloud-translate (>=3.3.1)
Requires-Dist: pandas
